rideshare_comparison_mcp/__init__.py
rideshare_comparison_mcp/__main__.py
rideshare_comparison_mcp/server.py
rideshare_comparison_mcp-1.0.0.dist-info/METADATA
rideshare_comparison_mcp-1.0.0.dist-info/WHEEL
rideshare_comparison_mcp-1.0.0.dist-info/entry_points.txt
rideshare_comparison_mcp-1.0.0.dist-info/RECORD
