Metadata-Version: 2.4
Name: rideshare-comparison-mcp
Version: 1.0.0
Summary: Compare Uber and Lyft prices via MCP for Claude Desktop
Project-URL: Homepage, https://github.com/wmarceau/rideshare-comparison-mcp
Project-URL: Repository, https://github.com/wmarceau/rideshare-comparison-mcp
Author-email: William Marceau <william@marceausolutions.com>
License: MIT
Keywords: claude,lyft,mcp,price-comparison,rideshare,uber
Classifier: Development Status :: 4 - Beta
Classifier: Intended Audience :: Developers
Classifier: License :: OSI Approved :: MIT License
Classifier: Programming Language :: Python :: 3
Classifier: Programming Language :: Python :: 3.10
Classifier: Programming Language :: Python :: 3.11
Classifier: Programming Language :: Python :: 3.12
Requires-Python: >=3.10
Requires-Dist: httpx>=0.24.0
